ttnn_visualizer/__init__.py
ttnn_visualizer/app.py
ttnn_visualizer/csv_queries.py
ttnn_visualizer/decorators.py
ttnn_visualizer/enums.py
ttnn_visualizer/exceptions.py
ttnn_visualizer/extensions.py
ttnn_visualizer/file_uploads.py
ttnn_visualizer/instances.py
ttnn_visualizer/models.py
ttnn_visualizer/pytest_plugin.py
ttnn_visualizer/queries.py
ttnn_visualizer/serializers.py
ttnn_visualizer/settings.py
ttnn_visualizer/sftp_operations.py
ttnn_visualizer/sockets.py
ttnn_visualizer/ssh_client.py
ttnn_visualizer/utils.py
ttnn_visualizer/views.py
ttnn_visualizer/static/index.html
ttnn_visualizer/static/assets/allPaths-BZLVCrxa.js
ttnn_visualizer/static/assets/allPathsLoader-7-MAALae.js
ttnn_visualizer/static/assets/index-BZITDwoa.js
ttnn_visualizer/static/assets/index-DS75jGv-.css
ttnn_visualizer/static/assets/index-ryWOUYjC.js
ttnn_visualizer/static/assets/index-voJy5fZe.js
ttnn_visualizer/static/assets/site-BTBrvHC5.webmanifest
ttnn_visualizer/static/assets/splitPathsBySizeLoader-CpZbtknp.js
ttnn_visualizer/static/favicon/android-chrome-192x192.png
ttnn_visualizer/static/favicon/android-chrome-512x512.png
ttnn_visualizer/static/favicon/favicon-32x32.png
ttnn_visualizer/static/favicon/favicon.svg
ttnn_visualizer/static/sample-data/cluster-desc.yaml
ttnn_visualizer/tests/__init__.py
ttnn_visualizer/tests/test_queries.py
ttnn_visualizer/tests/test_serializers.py
ttnn_visualizer/tests/test_utils.py
ttnn_visualizer-0.68.0.dist-info/licenses/LICENSE
ttnn_visualizer-0.68.0.dist-info/licenses/LICENSE_understanding.txt
ttnn_visualizer-0.68.0.dist-info/METADATA
ttnn_visualizer-0.68.0.dist-info/WHEEL
ttnn_visualizer-0.68.0.dist-info/entry_points.txt
ttnn_visualizer-0.68.0.dist-info/top_level.txt
ttnn_visualizer-0.68.0.dist-info/RECORD
