Metadata-Version: 2.4
Name: ttnn_visualizer
Version: 0.68.0
Summary: TT-NN Visualizer
Classifier: Programming Language :: Python :: 3
Classifier: License :: OSI Approved :: MIT License
Classifier: Operating System :: OS Independent
Requires-Python: >=3.10
License-File: LICENSE
License-File: LICENSE_understanding.txt
Requires-Dist: build
Requires-Dist: Flask-Cors==6.0.0
Requires-Dist: flask-socketio==5.4.1
Requires-Dist: flask-sqlalchemy==3.1.1
Requires-Dist: Flask-Static-Digest==0.4.1
Requires-Dist: Flask==3.1.1
Requires-Dist: gevent==24.10.2
Requires-Dist: gunicorn~=23.0.0
Requires-Dist: orjson>=3.9.0
Requires-Dist: pandas==2.2.3
Requires-Dist: pydantic_core==2.27.1
Requires-Dist: pydantic==2.10.3
Requires-Dist: python-dotenv==1.0.1
Requires-Dist: PyYAML==6.0.2
Requires-Dist: tt-perf-report==1.1.14
Requires-Dist: uvicorn==0.30.1
Requires-Dist: zstd==1.5.7.0
Provides-Extra: dev
Requires-Dist: black==25.1.0; extra == "dev"
Requires-Dist: isort==6.0.1; extra == "dev"
Requires-Dist: mypy; extra == "dev"
Requires-Dist: playwright==1.48.0; extra == "dev"
Requires-Dist: pytest==8.4.1; extra == "dev"
Provides-Extra: docs
Requires-Dist: myst_parser==4.0.1; extra == "docs"
Requires-Dist: nbsphinx==0.9.7; extra == "docs"
Requires-Dist: sphinx_rtd_theme==3.0.2; extra == "docs"
Requires-Dist: sphinx_sitemap==2.9.0; extra == "docs"
Requires-Dist: sphinx==8.1.3; extra == "docs"
Requires-Dist: sphinxcontrib.email==0.3.6; extra == "docs"
Dynamic: license-file
